BetterThreads/Pipe.py
BetterThreads/PooledThread.py
BetterThreads/ThreadPool.py
BetterThreads/__init__.py
better_threads-2.0.7.dist-info/METADATA
better_threads-2.0.7.dist-info/WHEEL
better_threads-2.0.7.dist-info/top_level.txt
better_threads-2.0.7.dist-info/RECORD
