Metadata-Version: 2.1
Name: better-threads
Version: 2.0.7
Summary: A package that provides extended control over threads
Home-page: https://github.com/ItsYasiru/Better-Threads
Author: Yasiru
Author-email: yasiru.dharmathilaka@gmail.com
License: MIT
Platform: UNKNOWN
Classifier: License :: OSI Approved :: MIT License
Classifier: Programming Language :: Python :: 3
Classifier: Programming Language :: Python :: 3.7
Classifier: Programming Language :: Python :: 3.9
